scsapi/__init__.py
scsapi/address.py
scsapi/exceptions.py
scsapi/order.py
scsapi/product.py
scsapi-0.1.1.dist-info/LICENSE
scsapi-0.1.1.dist-info/METADATA
scsapi-0.1.1.dist-info/WHEEL
scsapi-0.1.1.dist-info/top_level.txt
scsapi-0.1.1.dist-info/RECORD
