Metadata-Version: 2.1
Name: scsapi
Version: 0.1.1
Summary: A third-party API to connect to, browse, and interact with SpeedCubeShop.
Home-page: https://github.com/MysteryBlokHed/scsapi
Author: Adam Thompson-Sharpe
Author-email: adamthompsonsharpe@gmail.com
License: MIT License
Platform: UNKNOWN
Classifier: Programming Language :: Python :: 3.6
Classifier: License :: OSI Approved :: MIT License
Classifier: Operating System :: OS Independent
Requires-Dist: requests
Requires-Dist: beautifulsoup4
